{
    "10/01/2019": {
        "open": 179.15,
        "high": 179.84,
        "low": 174.88,
        "close": 175.81,
        "volume": 17261561
    },
    "10/02/2019": {
        "open": 174.84,
        "high": 176.53,
        "low": 173.09,
        "close": 174.6,
        "volume": 16374150
    },
    "10/03/2019": {
        "open": 175.57,
        "high": 179.84,
        "low": 173.63,
        "close": 179.38,
        "volume": 16789320
    },
    "10/04/2019": {
        "open": 179.55,
        "high": 180.98,
        "low": 178.1,
        "close": 180.45,
        "volume": 10476400
    },
    "10/07/2019": {
        "open": 180.0,
        "high": 181.18,
        "low": 178.09,
        "close": 179.68,
        "volume": 9359793
    },
    "10/08/2019": {
        "open": 178.26,
        "high": 180.37,
        "low": 177.72,
        "close": 177.75,
        "volume": 10084900
    },
    "10/09/2019": {
        "open": 179.16,
        "high": 180.72,
        "low": 177.94,
        "close": 179.85,
        "volume": 7648874
    },
    "10/10/2019": {
        "open": 180.32,
        "high": 181.61,
        "low": 179.17,
        "close": 180.03,
        "volume": 8980978
    },
    "10/11/2019": {
        "open": 182.15,
        "high": 186.49,
        "low": 182.14,
        "close": 184.19,
        "volume": 14998750
    },
    "10/14/2019": {
        "open": 184.2,
        "high": 184.62,
        "low": 182.57,
        "close": 183.28,
        "volume": 7203665
    },
    "10/15/2019": {
        "open": 183.8,
        "high": 190.38,
        "low": 183.66,
        "close": 188.89,
        "volume": 15143120
    },
    "10/16/2019": {
        "open": 188.32,
        "high": 189.7,
        "low": 186.9,
        "close": 189.55,
        "volume": 10560340
    },
    "10/17/2019": {
        "open": 190.3,
        "high": 190.84,
        "low": 188.77,
        "close": 190.39,
        "volume": 9761548
    },
    "10/18/2019": {
        "open": 190.23,
        "high": 191.49,
        "low": 183.92,
        "close": 185.85,
        "volume": 16882859
    },
    "10/21/2019": {
        "open": 187.04,
        "high": 189.91,
        "low": 186.75,
        "close": 189.76,
        "volume": 8580744
    },
    "10/22/2019": {
        "open": 190.0,
        "high": 190.65,
        "low": 181.5,
        "close": 182.34,
        "volume": 19854189
    },
    "10/23/2019": {
        "open": 182.01,
        "high": 186.38,
        "low": 182.0,
        "close": 186.15,
        "volume": 12370820
    },
    "10/24/2019": {
        "open": 184.62,
        "high": 186.73,
        "low": 182.8,
        "close": 186.38,
        "volume": 11505410
    },
    "10/25/2019": {
        "open": 185.83,
        "high": 189.0,
        "low": 185.09,
        "close": 187.89,
        "volume": 8061240
    },
    "10/28/2019": {
        "open": 187.2,
        "high": 189.53,
        "low": 185.08,
        "close": 189.4,
        "volume": 13657870
    },
    "10/29/2019": {
        "open": 191.69,
        "high": 192.53,
        "low": 188.47,
        "close": 189.31,
        "volume": 13574870
    },
    "10/30/2019": {
        "open": 189.56,
        "high": 190.45,
        "low": 185.98,
        "close": 188.25,
        "volume": 28734561
    },
    "10/31/2019": {
        "open": 196.7,
        "high": 198.09,
        "low": 188.25,
        "close": 191.65,
        "volume": 42286527
    },
    "11/01/2019": {
        "open": 192.85,
        "high": 194.11,
        "low": 189.91,
        "close": 193.62,
        "volume": 21711830
    },
    "11/04/2019": {
        "open": 194.55,
        "high": 197.37,
        "low": 193.81,
        "close": 194.72,
        "volume": 16371290
    },
    "11/05/2019": {
        "open": 195.37,
        "high": 195.75,
        "low": 193.6,
        "close": 194.32,
        "volume": 9941954
    },
    "11/06/2019": {
        "open": 194.03,
        "high": 194.37,
        "low": 191.35,
        "close": 191.55,
        "volume": 10973020
    },
    "11/07/2019": {
        "open": 191.91,
        "high": 193.44,
        "low": 189.47,
        "close": 190.42,
        "volume": 13473000
    },
    "11/08/2019": {
        "open": 190.0,
        "high": 192.34,
        "low": 189.7,
        "close": 190.84,
        "volume": 10764780
    },
    "11/11/2019": {
        "open": 189.93,
        "high": 190.08,
        "low": 188.54,
        "close": 189.61,
        "volume": 8637768
    },
    "11/12/2019": {
        "open": 190.0,
        "high": 195.06,
        "low": 189.74,
        "close": 194.47,
        "volume": 17615449
    },
    "11/13/2019": {
        "open": 194.7,
        "high": 195.7,
        "low": 192.74,
        "close": 193.19,
        "volume": 11009800
    },
    "11/14/2019": {
        "open": 192.93,
        "high": 194.03,
        "low": 191.45,
        "close": 193.15,
        "volume": 9059897
    },
    "11/15/2019": {
        "open": 194.26,
        "high": 195.3,
        "low": 193.38,
        "close": 195.1,
        "volume": 11530230
    },
    "11/18/2019": {
        "open": 194.56,
        "high": 198.63,
        "low": 193.05,
        "close": 197.4,
        "volume": 16176110
    },
    "11/19/2019": {
        "open": 197.4,
        "high": 200.0,
        "low": 196.86,
        "close": 199.32,
        "volume": 19070289
    },
    "11/20/2019": {
        "open": 198.58,
        "high": 199.59,
        "low": 195.43,
        "close": 197.51,
        "volume": 12370240
    },
    "11/21/2019": {
        "open": 197.42,
        "high": 199.09,
        "low": 196.86,
        "close": 197.93,
        "volume": 12130990
    },
    "11/22/2019": {
        "open": 198.38,
        "high": 199.3,
        "low": 197.62,
        "close": 198.82,
        "volume": 9959817
    },
    "11/25/2019": {
        "open": 199.52,
        "high": 200.97,
        "low": 199.25,
        "close": 199.79,
        "volume": 15286440
    },
    "11/26/2019": {
        "open": 200.0,
        "high": 200.15,
        "low": 198.04,
        "close": 198.97,
        "volume": 11748660
    },
    "11/27/2019": {
        "open": 199.9,
        "high": 203.14,
        "low": 199.42,
        "close": 202.0,
        "volume": 12760570
    },
    "11/29/2019": {
        "open": 201.6,
        "high": 203.8,
        "low": 201.21,
        "close": 201.64,
        "volume": 7985231
    },
    "12/02/2019": {
        "open": 202.13,
        "high": 202.18,
        "low": 198.05,
        "close": 199.7,
        "volume": 11542020
    },
    "12/03/2019": {
        "open": 197.6,
        "high": 198.93,
        "low": 195.08,
        "close": 198.82,
        "volume": 13014170
    },
    "12/04/2019": {
        "open": 200.0,
        "high": 200.03,
        "low": 198.05,
        "close": 198.71,
        "volume": 8459939
    },
    "12/05/2019": {
        "open": 199.86,
        "high": 201.29,
        "low": 198.21,
        "close": 199.36,
        "volume": 9755350
    },
    "12/06/2019": {
        "open": 200.5,
        "high": 201.57,
        "low": 200.06,
        "close": 201.05,
        "volume": 12279530
    },
    "12/09/2019": {
        "open": 200.65,
        "high": 203.14,
        "low": 200.21,
        "close": 201.34,
        "volume": 12013220
    },
    "12/10/2019": {
        "open": 201.66,
        "high": 202.05,
        "low": 200.15,
        "close": 200.87,
        "volume": 9485568
    },
    "12/11/2019": {
        "open": 200.28,
        "high": 202.63,
        "low": 200.28,
        "close": 202.26,
        "volume": 8041827
    },
    "12/12/2019": {
        "open": 202.35,
        "high": 203.66,
        "low": 194.1,
        "close": 196.75,
        "volume": 23766990
    },
    "12/13/2019": {
        "open": 196.4,
        "high": 196.8,
        "low": 193.17,
        "close": 194.11,
        "volume": 18605650
    },
    "12/16/2019": {
        "open": 195.27,
        "high": 199.12,
        "low": 194.81,
        "close": 197.92,
        "volume": 14922730
    },
    "12/17/2019": {
        "open": 198.84,
        "high": 199.0,
        "low": 196.13,
        "close": 198.39,
        "volume": 10177610
    },
    "12/18/2019": {
        "open": 200.09,
        "high": 204.3,
        "low": 200.09,
        "close": 202.5,
        "volume": 23284750
    },
    "12/19/2019": {
        "open": 202.78,
        "high": 206.3,
        "low": 202.51,
        "close": 206.06,
        "volume": 16808180
    },
    "12/20/2019": {
        "open": 207.48,
        "high": 207.71,
        "low": 203.43,
        "close": 206.3,
        "volume": 27315230
    },
    "12/23/2019": {
        "open": 206.7,
        "high": 208.59,
        "low": 205.68,
        "close": 206.18,
        "volume": 13353190
    },
    "12/24/2019": {
        "open": 206.3,
        "high": 206.79,
        "low": 205.0,
        "close": 205.12,
        "volume": 6046273
    },
    "12/26/2019": {
        "open": 205.57,
        "high": 207.82,
        "low": 205.31,
        "close": 207.79,
        "volume": 9368273
    },
    "12/27/2019": {
        "open": 208.67,
        "high": 208.93,
        "low": 206.59,
        "close": 208.1,
        "volume": 10287630
    },
    "12/30/2019": {
        "open": 207.86,
        "high": 207.9,
        "low": 203.9,
        "close": 204.41,
        "volume": 10534440
    },
    "12/31/2019": {
        "open": 204.0,
        "high": 205.56,
        "low": 203.6,
        "close": 205.25,
        "volume": 8962756
    },
    "01/02/2020": {
        "open": 206.75,
        "high": 209.79,
        "low": 206.27,
        "close": 209.78,
        "volume": 12090710
    },
    "01/03/2020": {
        "open": 207.21,
        "high": 210.4,
        "low": 206.95,
        "close": 208.67,
        "volume": 11197420
    },
    "01/06/2020": {
        "open": 206.7,
        "high": 212.78,
        "low": 206.52,
        "close": 212.6,
        "volume": 17073859
    },
    "01/07/2020": {
        "open": 212.82,
        "high": 214.58,
        "low": 211.75,
        "close": 213.06,
        "volume": 15111860
    },
    "01/08/2020": {
        "open": 213.0,
        "high": 216.24,
        "low": 212.61,
        "close": 215.22,
        "volume": 13492700
    },
    "01/09/2020": {
        "open": 217.54,
        "high": 218.38,
        "low": 216.28,
        "close": 218.3,
        "volume": 12679580
    },
    "01/10/2020": {
        "open": 219.2,
        "high": 219.88,
        "low": 217.42,
        "close": 218.06,
        "volume": 12127430
    },
    "01/13/2020": {
        "open": 219.6,
        "high": 221.97,
        "low": 219.21,
        "close": 221.91,
        "volume": 14494520
    },
    "01/14/2020": {
        "open": 221.61,
        "high": 222.38,
        "low": 218.63,
        "close": 219.06,
        "volume": 13315360
    },
    "01/15/2020": {
        "open": 220.61,
        "high": 221.68,
        "low": 220.14,
        "close": 221.15,
        "volume": 10036480
    },
    "01/16/2020": {
        "open": 222.57,
        "high": 222.63,
        "low": 220.39,
        "close": 221.77,
        "volume": 10015290
    },
    "01/17/2020": {
        "open": 222.03,
        "high": 222.29,
        "low": 220.53,
        "close": 222.14,
        "volume": 15905940
    },
    "01/21/2020": {
        "open": 222.16,
        "high": 222.37,
        "low": 219.12,
        "close": 221.44,
        "volume": 14275780
    },
    "01/22/2020": {
        "open": 222.31,
        "high": 222.75,
        "low": 221.28,
        "close": 221.32,
        "volume": 12212810
    },
    "01/23/2020": {
        "open": 220.75,
        "high": 221.49,
        "low": 219.27,
        "close": 219.76,
        "volume": 11195000
    },
    "01/24/2020": {
        "open": 220.8,
        "high": 221.78,
        "low": 216.11,
        "close": 217.94,
        "volume": 11905820
    },
    "01/27/2020": {
        "open": 213.1,
        "high": 216.06,
        "low": 212.5,
        "close": 214.87,
        "volume": 13810660
    },
    "01/28/2020": {
        "open": 216.14,
        "high": 218.74,
        "low": 213.52,
        "close": 217.79,
        "volume": 13413840
    },
    "01/29/2020": {
        "open": 221.44,
        "high": 224.2,
        "low": 218.45,
        "close": 223.23,
        "volume": 33610008
    },
    "01/30/2020": {
        "open": 206.53,
        "high": 211.43,
        "low": 204.75,
        "close": 209.53,
        "volume": 48775500
    },
    "01/31/2020": {
        "open": 208.43,
        "high": 208.69,
        "low": 201.06,
        "close": 201.91,
        "volume": 31359920
    },
    "02/03/2020": {
        "open": 203.44,
        "high": 205.14,
        "low": 202.5,
        "close": 204.19,
        "volume": 15510510
    },
    "02/04/2020": {
        "open": 206.62,
        "high": 210.6,
        "low": 205.2,
        "close": 209.83,
        "volume": 19628891
    },
    "02/05/2020": {
        "open": 212.51,
        "high": 212.73,
        "low": 208.71,
        "close": 210.11,
        "volume": 12538150
    },
    "02/06/2020": {
        "open": 210.47,
        "high": 211.19,
        "low": 209.34,
        "close": 210.85,
        "volume": 10567530
    },
    "02/07/2020": {
        "open": 210.3,
        "high": 212.82,
        "low": 209.93,
        "close": 212.33,
        "volume": 12242530
    },
    "02/10/2020": {
        "open": 211.52,
        "high": 213.8,
        "low": 210.66,
        "close": 213.06,
        "volume": 11856350
    },
    "02/11/2020": {
        "open": 210.19,
        "high": 210.86,
        "low": 206.51,
        "close": 207.19,
        "volume": 25030811
    },
    "02/12/2020": {
        "open": 207.85,
        "high": 211.22,
        "low": 207.4,
        "close": 210.76,
        "volume": 13813700
    },
    "02/13/2020": {
        "open": 209.52,
        "high": 214.33,
        "low": 209.18,
        "close": 213.14,
        "volume": 15396630
    },
    "02/14/2020": {
        "open": 214.0,
        "high": 214.93,
        "low": 212.65,
        "close": 214.18,
        "volume": 10741750
    },
    "02/18/2020": {
        "open": 213.55,
        "high": 217.98,
        "low": 213.4,
        "close": 217.8,
        "volume": 15630030
    },
    "02/19/2020": {
        "open": 217.99,
        "high": 218.32,
        "low": 216.11,
        "close": 217.49,
        "volume": 12135110
    },
    "02/20/2020": {
        "open": 216.52,
        "high": 218.77,
        "low": 212.95,
        "close": 214.58,
        "volume": 13109210
    },
    "02/21/2020": {
        "open": 213.48,
        "high": 214.24,
        "low": 208.83,
        "close": 210.18,
        "volume": 14098430
    },
    "02/24/2020": {
        "open": 201.8,
        "high": 203.65,
        "low": 198.17,
        "close": 200.72,
        "volume": 23080061
    },
    "02/25/2020": {
        "open": 202.25,
        "high": 203.5,
        "low": 195.95,
        "close": 196.77,
        "volume": 21433490
    },
    "02/26/2020": {
        "open": 197.19,
        "high": 201.21,
        "low": 195.49,
        "close": 197.2,
        "volume": 16555211
    },
    "02/27/2020": {
        "open": 191.82,
        "high": 195.88,
        "low": 189.5,
        "close": 189.75,
        "volume": 21682631
    },
    "02/28/2020": {
        "open": 182.7,
        "high": 192.74,
        "low": 181.82,
        "close": 192.47,
        "volume": 32583490
    },
    "03/02/2020": {
        "open": 194.03,
        "high": 196.57,
        "low": 188.85,
        "close": 196.44,
        "volume": 24948961
    },
    "03/03/2020": {
        "open": 196.22,
        "high": 197.24,
        "low": 183.97,
        "close": 185.89,
        "volume": 27984100
    },
    "03/04/2020": {
        "open": 189.17,
        "high": 191.83,
        "low": 186.39,
        "close": 191.76,
        "volume": 23062471
    },
    "03/05/2020": {
        "open": 186.78,
        "high": 188.99,
        "low": 183.89,
        "close": 185.17,
        "volume": 19333430
    },
    "03/06/2020": {
        "open": 178.33,
        "high": 183.78,
        "low": 176.26,
        "close": 181.09,
        "volume": 24559551
    },
    "03/09/2020": {
        "open": 169.6,
        "high": 175.0,
        "low": 165.19,
        "close": 169.5,
        "volume": 29949039
    },
    "03/10/2020": {
        "open": 174.67,
        "high": 178.29,
        "low": 169.5,
        "close": 178.19,
        "volume": 24517789
    },
    "03/11/2020": {
        "open": 174.01,
        "high": 175.88,
        "low": 167.66,
        "close": 170.24,
        "volume": 20397199
    },
    "03/12/2020": {
        "open": 159.54,
        "high": 166.6,
        "low": 154.34,
        "close": 154.47,
        "volume": 43266340
    },
    "03/13/2020": {
        "open": 163.53,
        "high": 170.79,
        "low": 157.6,
        "close": 170.28,
        "volume": 35028633
    },
    "03/16/2020": {
        "open": 152.32,
        "high": 159.13,
        "low": 143.1,
        "close": 146.01,
        "volume": 39120422
    },
    "03/17/2020": {
        "open": 150.74,
        "high": 153.94,
        "low": 140.0,
        "close": 149.42,
        "volume": 34255602
    },
    "03/18/2020": {
        "open": 139.75,
        "high": 148.18,
        "low": 137.1,
        "close": 146.96,
        "volume": 37553141
    },
    "03/19/2020": {
        "open": 146.62,
        "high": 159.93,
        "low": 144.8,
        "close": 153.13,
        "volume": 39862312
    },
    "03/20/2020": {
        "open": 156.02,
        "high": 159.27,
        "low": 148.0,
        "close": 149.73,
        "volume": 32568400
    },
    "03/23/2020": {
        "open": 149.66,
        "high": 152.31,
        "low": 142.25,
        "close": 148.1,
        "volume": 29830770
    },
    "03/24/2020": {
        "open": 155.21,
        "high": 161.31,
        "low": 152.57,
        "close": 160.98,
        "volume": 30440369
    },
    "03/25/2020": {
        "open": 158.92,
        "high": 162.99,
        "low": 153.06,
        "close": 156.21,
        "volume": 35184273
    },
    "03/26/2020": {
        "open": 158.25,
        "high": 164.0,
        "low": 157.02,
        "close": 163.34,
        "volume": 26579020
    },
    "03/27/2020": {
        "open": 158.2,
        "high": 160.09,
        "low": 154.75,
        "close": 156.79,
        "volume": 24879869
    },
    "03/30/2020": {
        "open": 159.18,
        "high": 166.75,
        "low": 158.06,
        "close": 165.95,
        "volume": 22515230
    },
    "03/31/2020": {
        "open": 165.48,
        "high": 170.93,
        "low": 164.2,
        "close": 166.8,
        "volume": 23676279
    },
    "04/01/2020": {
        "open": 161.62,
        "high": 164.15,
        "low": 158.04,
        "close": 159.6,
        "volume": 19507561
    },
    "04/02/2020": {
        "open": 159.1,
        "high": 161.35,
        "low": 155.92,
        "close": 158.19,
        "volume": 20886311
    },
    "04/03/2020": {
        "open": 157.15,
        "high": 157.91,
        "low": 150.83,
        "close": 154.18,
        "volume": 25983320
    },
    "04/06/2020": {
        "open": 160.15,
        "high": 166.2,
        "low": 158.51,
        "close": 165.55,
        "volume": 28359600
    },
    "04/07/2020": {
        "open": 171.79,
        "high": 173.39,
        "low": 166.01,
        "close": 168.83,
        "volume": 31411920
    },
    "04/08/2020": {
        "open": 171.25,
        "high": 175.0,
        "low": 167.74,
        "close": 174.28,
        "volume": 21664199
    },
    "04/09/2020": {
        "open": 175.9,
        "high": 177.08,
        "low": 171.57,
        "close": 175.19,
        "volume": 23534289
    },
    "04/13/2020": {
        "open": 173.67,
        "high": 175.0,
        "low": 169.45,
        "close": 174.79,
        "volume": 19355359
    },
    "04/14/2020": {
        "open": 178.98,
        "high": 181.23,
        "low": 176.62,
        "close": 178.17,
        "volume": 21011820
    },
    "04/15/2020": {
        "open": 175.19,
        "high": 178.19,
        "low": 172.82,
        "close": 176.97,
        "volume": 17423000
    },
    "04/16/2020": {
        "open": 177.95,
        "high": 178.05,
        "low": 172.51,
        "close": 176.25,
        "volume": 23593230
    },
    "04/17/2020": {
        "open": 179.2,
        "high": 180.28,
        "low": 176.66,
        "close": 179.24,
        "volume": 20974750
    },
    "04/20/2020": {
        "open": 177.41,
        "high": 180.5,
        "low": 176.77,
        "close": 178.24,
        "volume": 16110580
    },
    "04/21/2020": {
        "open": 175.25,
        "high": 175.38,
        "low": 168.34,
        "close": 170.8,
        "volume": 24850529
    },
    "04/22/2020": {
        "open": 178.45,
        "high": 184.78,
        "low": 178.14,
        "close": 182.28,
        "volume": 33369930
    },
    "04/23/2020": {
        "open": 184.08,
        "high": 187.05,
        "low": 183.15,
        "close": 185.13,
        "volume": 21426600
    },
    "04/24/2020": {
        "open": 183.23,
        "high": 190.41,
        "low": 180.83,
        "close": 190.07,
        "volume": 28868529
    },
    "04/27/2020": {
        "open": 192.66,
        "high": 193.75,
        "low": 187.41,
        "close": 187.5,
        "volume": 29197750
    },
    "04/28/2020": {
        "open": 188.66,
        "high": 189.2,
        "low": 182.56,
        "close": 182.91,
        "volume": 21730990
    },
    "04/29/2020": {
        "open": 190.93,
        "high": 196.91,
        "low": 190.0,
        "close": 194.19,
        "volume": 45954520
    },
    "04/30/2020": {
        "open": 206.92,
        "high": 209.69,
        "low": 201.57,
        "close": 204.71,
        "volume": 46230121
    },
    "05/01/2020": {
        "open": 201.6,
        "high": 207.28,
        "low": 199.05,
        "close": 202.27,
        "volume": 30415580
    },
    "05/04/2020": {
        "open": 200.2,
        "high": 205.91,
        "low": 198.76,
        "close": 205.26,
        "volume": 19250670
    },
    "05/05/2020": {
        "open": 207.02,
        "high": 210.38,
        "low": 206.5,
        "close": 207.07,
        "volume": 21071221
    },
    "05/06/2020": {
        "open": 208.12,
        "high": 211.6,
        "low": 206.66,
        "close": 208.47,
        "volume": 21856961
    },
    "05/07/2020": {
        "open": 211.16,
        "high": 211.6,
        "low": 209.04,
        "close": 211.26,
        "volume": 15151980
    },
    "05/08/2020": {
        "open": 212.24,
        "high": 213.21,
        "low": 210.85,
        "close": 212.35,
        "volume": 12524050
    },
    "05/11/2020": {
        "open": 210.89,
        "high": 215.0,
        "low": 210.37,
        "close": 213.18,
        "volume": 12911950
    },
    "05/12/2020": {
        "open": 213.29,
        "high": 215.28,
        "low": 210.0,
        "close": 210.1,
        "volume": 14704650
    },
    "05/13/2020": {
        "open": 209.43,
        "high": 210.78,
        "low": 202.11,
        "close": 205.1,
        "volume": 20684561
    },
    "05/14/2020": {
        "open": 202.56,
        "high": 206.93,
        "low": 200.69,
        "close": 206.81,
        "volume": 17178949
    },
    "05/15/2020": {
        "open": 205.27,
        "high": 211.34,
        "low": 204.12,
        "close": 210.88,
        "volume": 19383150
    },
    "05/18/2020": {
        "open": 212.15,
        "high": 214.64,
        "low": 210.94,
        "close": 213.19,
        "volume": 20167439
    },
    "05/19/2020": {
        "open": 213.27,
        "high": 220.49,
        "low": 212.83,
        "close": 216.88,
        "volume": 31843150
    },
    "05/20/2020": {
        "open": 223.5,
        "high": 231.34,
        "low": 223.19,
        "close": 229.97,
        "volume": 50162879
    },
    "05/21/2020": {
        "open": 234.72,
        "high": 237.2,
        "low": 231.2,
        "close": 231.39,
        "volume": 47782641
    },
    "05/22/2020": {
        "open": 231.51,
        "high": 235.99,
        "low": 228.74,
        "close": 234.91,
        "volume": 33925559
    },
    "05/26/2020": {
        "open": 239.77,
        "high": 240.9,
        "low": 231.67,
        "close": 232.2,
        "volume": 33178320
    },
    "05/27/2020": {
        "open": 229.07,
        "high": 230.56,
        "low": 221.13,
        "close": 229.14,
        "volume": 34697551
    },
    "05/28/2020": {
        "open": 224.3,
        "high": 231.63,
        "low": 224.0,
        "close": 225.46,
        "volume": 29423010
    },
    "05/29/2020": {
        "open": 225.2,
        "high": 227.49,
        "low": 222.88,
        "close": 225.09,
        "volume": 23322480
    },
    "06/01/2020": {
        "open": 224.59,
        "high": 232.44,
        "low": 223.5,
        "close": 231.91,
        "volume": 18223840
    },
    "06/02/2020": {
        "open": 230.94,
        "high": 233.0,
        "low": 226.56,
        "close": 232.72,
        "volume": 20919020
    },
    "06/03/2020": {
        "open": 232.11,
        "high": 232.65,
        "low": 228.53,
        "close": 230.16,
        "volume": 15380280
    },
    "06/04/2020": {
        "open": 229.56,
        "high": 231.63,
        "low": 224.61,
        "close": 226.29,
        "volume": 17041480
    },
    "06/05/2020": {
        "open": 226.71,
        "high": 231.35,
        "low": 225.31,
        "close": 230.77,
        "volume": 16750439
    },
    "06/08/2020": {
        "open": 229.03,
        "high": 231.55,
        "low": 227.41,
        "close": 231.4,
        "volume": 15466500
    },
    "06/09/2020": {
        "open": 231.52,
        "high": 239.77,
        "low": 230.41,
        "close": 238.67,
        "volume": 27462869
    },
    "06/10/2020": {
        "open": 240.96,
        "high": 241.21,
        "low": 235.28,
        "close": 236.73,
        "volume": 20720711
    },
    "06/11/2020": {
        "open": 229.94,
        "high": 232.89,
        "low": 223.55,
        "close": 224.43,
        "volume": 26708160
    },
    "06/12/2020": {
        "open": 229.9,
        "high": 231.66,
        "low": 224.5,
        "close": 228.58,
        "volume": 22091391
    },
    "06/15/2020": {
        "open": 225.09,
        "high": 233.77,
        "low": 224.8,
        "close": 232.5,
        "volume": 15340260
    },
    "06/16/2020": {
        "open": 237.14,
        "high": 238.46,
        "low": 233.0,
        "close": 235.65,
        "volume": 15236690
    },
    "06/17/2020": {
        "open": 235.0,
        "high": 237.59,
        "low": 231.73,
        "close": 235.53,
        "volume": 19578131
    },
    "06/18/2020": {
        "open": 234.99,
        "high": 236.14,
        "low": 232.15,
        "close": 235.94,
        "volume": 15782450
    },
    "06/19/2020": {
        "open": 237.79,
        "high": 240.83,
        "low": 235.55,
        "close": 238.79,
        "volume": 30081289
    },
    "06/22/2020": {
        "open": 238.56,
        "high": 240.7,
        "low": 236.91,
        "close": 239.22,
        "volume": 18917779
    },
    "06/23/2020": {
        "open": 241.28,
        "high": 245.19,
        "low": 239.86,
        "close": 242.24,
        "volume": 24017920
    },
    "06/24/2020": {
        "open": 241.2,
        "high": 243.22,
        "low": 232.68,
        "close": 234.02,
        "volume": 20834900
    },
    "06/25/2020": {
        "open": 234.62,
        "high": 237.3,
        "low": 232.74,
        "close": 235.68,
        "volume": 18704340
    },
    "06/26/2020": {
        "open": 232.64,
        "high": 233.09,
        "low": 215.4,
        "close": 216.08,
        "volume": 76343938
    },
    "06/29/2020": {
        "open": 209.75,
        "high": 220.75,
        "low": 207.11,
        "close": 220.64,
        "volume": 58514281
    },
    "06/30/2020": {
        "open": 220.59,
        "high": 227.5,
        "low": 218.47,
        "close": 227.07,
        "volume": 33927070
    },
    "07/01/2020": {
        "open": 228.5,
        "high": 239.0,
        "low": 227.56,
        "close": 237.55,
        "volume": 43399738
    },
    "07/02/2020": {
        "open": 239.0,
        "high": 240.0,
        "low": 232.61,
        "close": 233.42,
        "volume": 30633619
    },
    "07/06/2020": {
        "open": 233.76,
        "high": 240.4,
        "low": 232.27,
        "close": 240.28,
        "volume": 26206160
    },
    "07/07/2020": {
        "open": 239.41,
        "high": 247.65,
        "low": 238.82,
        "close": 240.86,
        "volume": 27887789
    },
    "07/08/2020": {
        "open": 238.11,
        "high": 246.99,
        "low": 236.59,
        "close": 243.58,
        "volume": 29791340
    },
    "07/09/2020": {
        "open": 245.0,
        "high": 246.53,
        "low": 239.24,
        "close": 244.5,
        "volume": 22174900
    },
    "07/10/2020": {
        "open": 243.69,
        "high": 245.49,
        "low": 239.32,
        "close": 245.07,
        "volume": 22982721
    },
    "07/13/2020": {
        "open": 247.01,
        "high": 250.15,
        "low": 238.42,
        "close": 239.0,
        "volume": 24674869
    },
    "07/14/2020": {
        "open": 236.76,
        "high": 240.33,
        "low": 232.03,
        "close": 239.73,
        "volume": 23378061
    },
    "07/15/2020": {
        "open": 241.55,
        "high": 244.82,
        "low": 238.05,
        "close": 240.28,
        "volume": 19133561
    },
    "07/16/2020": {
        "open": 238.0,
        "high": 241.76,
        "low": 236.33,
        "close": 240.93,
        "volume": 18880711
    },
    "07/17/2020": {
        "open": 241.0,
        "high": 244.16,
        "low": 237.86,
        "close": 242.03,
        "volume": 18152410
    },
    "07/20/2020": {
        "open": 240.06,
        "high": 246.05,
        "low": 235.64,
        "close": 245.42,
        "volume": 20872221
    },
    "07/21/2020": {
        "open": 246.22,
        "high": 246.91,
        "low": 240.08,
        "close": 241.75,
        "volume": 19409689
    },
    "07/22/2020": {
        "open": 240.26,
        "high": 241.9,
        "low": 238.12,
        "close": 239.87,
        "volume": 15427890
    },
    "07/23/2020": {
        "open": 239.63,
        "high": 242.42,
        "low": 231.75,
        "close": 232.6,
        "volume": 21771801
    },
    "07/24/2020": {
        "open": 230.19,
        "high": 233.49,
        "low": 226.9,
        "close": 230.71,
        "volume": 18325811
    },
    "07/27/2020": {
        "open": 231.46,
        "high": 234.95,
        "low": 230.83,
        "close": 233.5,
        "volume": 13163080
    },
    "07/28/2020": {
        "open": 234.63,
        "high": 234.96,
        "low": 229.83,
        "close": 230.12,
        "volume": 14170110
    },
    "07/29/2020": {
        "open": 231.14,
        "high": 233.7,
        "low": 230.31,
        "close": 233.29,
        "volume": 13588320
    },
    "07/30/2020": {
        "open": 230.22,
        "high": 234.89,
        "low": 229.0,
        "close": 234.5,
        "volume": 20615311
    },
    "07/31/2020": {
        "open": 255.82,
        "high": 255.85,
        "low": 249.0,
        "close": 253.67,
        "volume": 53030039
    },
    "08/03/2020": {
        "open": 252.65,
        "high": 255.4,
        "low": 250.33,
        "close": 251.96,
        "volume": 23134100
    },
    "08/04/2020": {
        "open": 251.56,
        "high": 252.8,
        "low": 247.43,
        "close": 249.83,
        "volume": 17183529
    },
    "08/05/2020": {
        "open": 250.19,
        "high": 252.27,
        "low": 247.77,
        "close": 249.12,
        "volume": 13088360
    },
    "08/06/2020": {
        "open": 249.04,
        "high": 266.6,
        "low": 248.67,
        "close": 265.28,
        "volume": 45241609
    },
    "08/07/2020": {
        "open": 264.08,
        "high": 278.89,
        "low": 263.43,
        "close": 268.44,
        "volume": 72766359
    },
    "08/10/2020": {
        "open": 268.04,
        "high": 273.86,
        "low": 259.69,
        "close": 263.0,
        "volume": 30248830
    },
    "08/11/2020": {
        "open": 260.19,
        "high": 265.92,
        "low": 255.13,
        "close": 256.13,
        "volume": 28238279
    },
    "08/12/2020": {
        "open": 258.97,
        "high": 263.9,
        "low": 258.11,
        "close": 259.89,
        "volume": 21428330
    },
    "08/13/2020": {
        "open": 261.55,
        "high": 265.16,
        "low": 259.57,
        "close": 261.3,
        "volume": 17373971
    },
    "08/14/2020": {
        "open": 262.31,
        "high": 262.65,
        "low": 258.68,
        "close": 261.24,
        "volume": 14792710
    },
    "08/17/2020": {
        "open": 262.5,
        "high": 264.1,
        "low": 259.4,
        "close": 261.16,
        "volume": 13351060
    },
    "08/18/2020": {
        "open": 260.95,
        "high": 265.15,
        "low": 259.26,
        "close": 262.34,
        "volume": 18690381
    },
    "08/19/2020": {
        "open": 261.39,
        "high": 267.91,
        "low": 261.35,
        "close": 262.59,
        "volume": 23291461
    },
    "08/20/2020": {
        "open": 261.5,
        "high": 269.63,
        "low": 261.46,
        "close": 269.01,
        "volume": 20299689
    },
    "08/21/2020": {
        "open": 268.69,
        "high": 270.49,
        "low": 266.42,
        "close": 267.01,
        "volume": 15538620
    },
    "08/24/2020": {
        "open": 271.07,
        "high": 277.25,
        "low": 268.77,
        "close": 271.39,
        "volume": 23685600
    },
    "08/25/2020": {
        "open": 272.41,
        "high": 283.09,
        "low": 270.26,
        "close": 280.82,
        "volume": 42127238
    },
    "08/26/2020": {
        "open": 284.0,
        "high": 304.67,
        "low": 284.0,
        "close": 303.91,
        "volume": 69015148
    },
    "08/27/2020": {
        "open": 300.16,
        "high": 301.23,
        "low": 292.02,
        "close": 293.22,
        "volume": 30301311
    },
    "08/28/2020": {
        "open": 295.0,
        "high": 297.23,
        "low": 290.98,
        "close": 293.66,
        "volume": 17172420
    },
    "08/31/2020": {
        "open": 293.95,
        "high": 296.88,
        "low": 291.55,
        "close": 293.2,
        "volume": 17345131
    },
    "09/01/2020": {
        "open": 294.71,
        "high": 301.49,
        "low": 292.71,
        "close": 295.44,
        "volume": 17320869
    },
    "09/02/2020": {
        "open": 298.88,
        "high": 303.6,
        "low": 293.05,
        "close": 302.5,
        "volume": 24341369
    },
    "09/03/2020": {
        "open": 295.99,
        "high": 297.6,
        "low": 283.63,
        "close": 291.12,
        "volume": 32294090
    },
    "09/04/2020": {
        "open": 287.25,
        "high": 289.0,
        "low": 271.14,
        "close": 282.73,
        "volume": 30333670
    },
    "09/08/2020": {
        "open": 271.28,
        "high": 279.3,
        "low": 269.42,
        "close": 271.16,
        "volume": 24864000
    },
    "09/09/2020": {
        "open": 275.77,
        "high": 278.48,
        "low": 271.35,
        "close": 273.72,
        "volume": 22918770
    },
    "09/10/2020": {
        "open": 275.51,
        "high": 279.16,
        "low": 267.03,
        "close": 268.09,
        "volume": 24814670
    },
    "09/11/2020": {
        "open": 270.06,
        "high": 271.39,
        "low": 262.64,
        "close": 266.61,
        "volume": 18913881
    },
    "09/14/2020": {
        "open": 270.95,
        "high": 276.64,
        "low": 265.7,
        "close": 266.15,
        "volume": 24093830
    },
    "09/15/2020": {
        "open": 270.67,
        "high": 274.52,
        "low": 269.3,
        "close": 272.42,
        "volume": 18478529
    },
    "09/16/2020": {
        "open": 267.29,
        "high": 272.44,
        "low": 261.79,
        "close": 263.52,
        "volume": 29207590
    },
    "09/17/2020": {
        "open": 258.28,
        "high": 261.5,
        "low": 250.19,
        "close": 254.82,
        "volume": 31281439
    },
    "09/18/2020": {
        "open": 258.41,
        "high": 259.2,
        "low": 250.05,
        "close": 252.53,
        "volume": 28130770
    },
    "09/21/2020": {
        "open": 247.54,
        "high": 249.95,
        "low": 244.13,
        "close": 248.15,
        "volume": 24709381
    },
    "09/22/2020": {
        "open": 253.31,
        "high": 255.32,
        "low": 248.22,
        "close": 254.75,
        "volume": 30293100
    },
    "09/23/2020": {
        "open": 255.26,
        "high": 257.99,
        "low": 248.15,
        "close": 249.02,
        "volume": 19641270
    },
    "09/24/2020": {
        "open": 246.5,
        "high": 252.24,
        "low": 245.62,
        "close": 249.53,
        "volume": 20006750
    },
    "09/25/2020": {
        "open": 249.4,
        "high": 255.75,
        "low": 246.61,
        "close": 254.82,
        "volume": 18351311
    },
    "09/28/2020": {
        "open": 259.4,
        "high": 259.6,
        "low": 254.82,
        "close": 256.82,
        "volume": 18826250
    },
    "09/29/2020": {
        "open": 257.81,
        "high": 263.33,
        "low": 256.9,
        "close": 261.79,
        "volume": 20215500
    },
    "09/30/2020": {
        "open": 261.98,
        "high": 266.09,
        "low": 260.1,
        "close": 261.9,
        "volume": 20142551
    },
    "10/01/2020": {
        "open": 265.35,
        "high": 268.33,
        "low": 264.8,
        "close": 266.63,
        "volume": 20009801
    }
}